envgen/__init__.py
envgen/cli.py
envgen/core.py
envgen_cli-0.2.2.dist-info/licenses/LICENSE
envgen_cli-0.2.2.dist-info/METADATA
envgen_cli-0.2.2.dist-info/WHEEL
envgen_cli-0.2.2.dist-info/entry_points.txt
envgen_cli-0.2.2.dist-info/top_level.txt
envgen_cli-0.2.2.dist-info/RECORD
