Metadata-Version: 2.4
Name: envgen-cli
Version: 0.2.2
Summary: Smart .env generator with auto-passwords, rich UI, and dotenv-vault support
Author-email: Den Ignatov <whickybravo388@gmail.com>
License: MIT
Project-URL: Homepage, https://github.com/whickybravo388/envgen
Project-URL: Repository, https://github.com/whickybravo388/envgen
Project-URL: Documentation, https://github.com/whickybravo388/envgen#readme
Classifier: Development Status :: 4 - Beta
Classifier: Environment :: Console
Classifier: Intended Audience :: Developers
Classifier: License :: OSI Approved :: MIT License
Classifier: Operating System :: OS Independent
Classifier: Programming Language :: Python :: 3
Classifier: Programming Language :: Python :: 3.8
Classifier: Programming Language :: Python :: 3.9
Classifier: Programming Language :: Python :: 3.10
Classifier: Programming Language :: Python :: 3.11
Classifier: Topic :: Software Development :: Code Generators
Classifier: Topic :: Utilities
Requires-Python: >=3.8
License-File: LICENSE
Requires-Dist: click>=8.0
Requires-Dist: rich>=13.0
Provides-Extra: vault
Dynamic: license-file
